{
   "url": "http://localhost:9000/api/events/reserva/99/ZMNI",
   "data": [
      {
         "idevent_reserva_grupo_agencia": "2",
         "id_group": "99",
         "idclv_propiedad": "ZMNI",
         "id_agencia": "0",
         "aprobado": "1",
         "usuario_aprobacion": "rcan",
         "folio_confirmacion": "123456798",
         "nombre_titular_reserva": "nombre",
         "apellido_titular_reserva": "Apellido",
         "nombre_agencia_reserva": "Despegar.com",
         "arrival_date": "2020-02-01 00:00:00",
         "departure_date": "2020-03-02 00:00:00",
         "cant_adults": "2",
         "cant_childs": "2",
         "cant_nights": "10",
         "cant_rooms": "10",
         "status": "1"
      },
      {
         "idevent_reserva_grupo_agencia": "7",
         "id_group": "99",
         "idclv_propiedad": "ZMNI",
         "id_agencia": "0",
         "aprobado": "1",
         "usuario_aprobacion": "rcan",
         "folio_confirmacion": "123455",
         "nombre_titular_reserva": "Servando",
         "apellido_titular_reserva": "Herrera",
         "nombre_agencia_reserva": "Despegar.com",
         "arrival_date": "2021-08-10 00:00:00",
         "departure_date": "2021-08-14 00:00:00",
         "cant_adults": "2",
         "cant_childs": "1",
         "cant_nights": "10",
         "cant_rooms": "2",
         "status": "1"
      },
      {
         "idevent_reserva_grupo_agencia": "13",
         "id_group": "99",
         "idclv_propiedad": "ZMNI",
         "id_agencia": "0",
         "aprobado": "0",
         "usuario_aprobacion": "rcan",
         "folio_confirmacion": "pending",
         "nombre_titular_reserva": "D. Clever",
         "apellido_titular_reserva": "Prueba",
         "nombre_agencia_reserva": "d.com",
         "arrival_date": "2021-06-05 00:00:00",
         "departure_date": "2021-06-09 00:00:00",
         "cant_adults": "2",
         "cant_childs": "0",
         "cant_nights": "0",
         "cant_rooms": "0",
         "status": "1"
      },
      {
         "idevent_reserva_grupo_agencia": "14",
         "id_group": "99",
         "idclv_propiedad": "ZMNI",
         "id_agencia": "0",
         "aprobado": "1",
         "usuario_aprobacion": "rcan",
         "folio_confirmacion": "11223365",
         "nombre_titular_reserva": "Ricardo",
         "apellido_titular_reserva": "Couoh",
         "nombre_agencia_reserva": "Despegar.com",
         "arrival_date": "2021-05-29 00:00:00",
         "departure_date": "2021-05-29 00:00:00",
         "cant_adults": "1",
         "cant_childs": "0",
         "cant_nights": "3",
         "cant_rooms": "1",
         "status": "1"
      },
      {
         "idevent_reserva_grupo_agencia": "15",
         "id_group": "99",
         "idclv_propiedad": " ",
         "id_agencia": " ",
         "aprobado": "0",
         "usuario_aprobacion": " ",
         "folio_confirmacion": " ",
         "nombre_titular_reserva": "avnel",
         "apellido_titular_reserva": "santos",
         "nombre_agencia_reserva": "test",
         "arrival_date": "2021-05-29 00:00:00",
         "departure_date": "2021-05-29 00:00:00",
         "cant_adults": "0",
         "cant_childs": "0",
         "cant_nights": "0",
         "cant_rooms": "0",
         "status": "1"
      },
      {
         "idevent_reserva_grupo_agencia": "16",
         "id_group": "99",
         "idclv_propiedad": " ",
         "id_agencia": " ",
         "aprobado": "0",
         "usuario_aprobacion": " ",
         "folio_confirmacion": " ",
         "nombre_titular_reserva": "avnel",
         "apellido_titular_reserva": "santos",
         "nombre_agencia_reserva": "test2",
         "arrival_date": "2021-05-30 00:00:00",
         "departure_date": "2021-05-30 00:00:00",
         "cant_adults": "0",
         "cant_childs": "0",
         "cant_nights": "0",
         "cant_rooms": "0",
         "status": "1"
      },
      {
         "idevent_reserva_grupo_agencia": "17",
         "id_group": "99",
         "idclv_propiedad": " ",
         "id_agencia": " ",
         "aprobado": "0",
         "usuario_aprobacion": " ",
         "folio_confirmacion": " ",
         "nombre_titular_reserva": "avnel",
         "apellido_titular_reserva": "santos",
         "nombre_agencia_reserva": "test2",
         "arrival_date": "2021-05-30 00:00:00",
         "departure_date": "2021-05-30 00:00:00",
         "cant_adults": "0",
         "cant_childs": "0",
         "cant_nights": "0",
         "cant_rooms": "0",
         "status": "1"
      },
      {
         "idevent_reserva_grupo_agencia": "18",
         "id_group": "99",
         "idclv_propiedad": " ",
         "id_agencia": " ",
         "aprobado": "0",
         "usuario_aprobacion": " ",
         "folio_confirmacion": " ",
         "nombre_titular_reserva": "avnel",
         "apellido_titular_reserva": "santos",
         "nombre_agencia_reserva": "test432",
         "arrival_date": "2021-05-31 00:00:00",
         "departure_date": "2021-05-31 00:00:00",
         "cant_adults": "0",
         "cant_childs": "0",
         "cant_nights": "0",
         "cant_rooms": "0",
         "status": "1"
      },
      {
         "idevent_reserva_grupo_agencia": "19",
         "id_group": "99",
         "idclv_propiedad": " ",
         "id_agencia": " ",
         "aprobado": "0",
         "usuario_aprobacion": " ",
         "folio_confirmacion": " ",
         "nombre_titular_reserva": "avnel",
         "apellido_titular_reserva": "santos",
         "nombre_agencia_reserva": "test",
         "arrival_date": "2021-05-30 00:00:00",
         "departure_date": "2021-05-31 00:00:00",
         "cant_adults": "0",
         "cant_childs": "0",
         "cant_nights": "0",
         "cant_rooms": "0",
         "status": "1"
      }
   ],
   "message": "OK",
   "code": 200,
   "error": false
}